{
    "zones": [
      {
        "key": "a",
        "name": "España",
        "locations": [
          { "name": "Álava", "coordinates": "42.8467,-2.6717", "key": "alava" },
          { "name": "Albacete", "coordinates": "38.9943,-1.8585", "key": "albacete" },
          { "name": "Alicante", "coordinates": "38.3452,-0.4810", "key": "alicante" },
          { "name": "Almería", "coordinates": "36.8340,-2.4637", "key": "almeria" },
          { "name": "Ávila", "coordinates": "40.6565,-4.6818", "key": "avila" },
          { "name": "Badajoz", "coordinates": "38.8794,-6.9707", "key": "badajoz" },
          { "name": "Baleares", "coordinates": "39.6953,3.0176", "key": "baleares" },
          { "name": "Barcelona", "coordinates": "41.3851,2.1734", "key": "barcelona" },
          { "name": "Burgos", "coordinates": "42.3439,-3.6969", "key": "burgos" },
          { "name": "Cáceres", "coordinates": "39.4769,-6.3723", "key": "caceres" },
          { "name": "Cádiz", "coordinates": "36.5271,-6.2886", "key": "cadiz" },
          { "name": "Castellón", "coordinates": "39.9864,-0.0513", "key": "castellon" },
          { "name": "Ciudad Real", "coordinates": "38.9848,-3.9274", "key": "ciudad_real" },
          { "name": "Córdoba", "coordinates": "37.8882,-4.7794", "key": "cordoba" },
          { "name": "Cuenca", "coordinates": "40.0704,-2.1374", "key": "cuenca" },
          { "name": "Girona", "coordinates": "41.9794,2.8214", "key": "girona" },
          { "name": "Granada", "coordinates": "37.1773,-3.5986", "key": "granada" },
          { "name": "Guadalajara", "coordinates": "40.6333,-3.1669", "key": "guadalajara" },
          { "name": "Guipúzcoa", "coordinates": "43.3128,-1.9763", "key": "guipuzcoa" },
          { "name": "Huelva", "coordinates": "37.2614,-6.9447", "key": "huelva" },
          { "name": "Huesca", "coordinates": "42.1401,-0.4089", "key": "huesca" },
          { "name": "Jaén", "coordinates": "37.7796,-3.7849", "key": "jaen" },
          { "name": "La Rioja", "coordinates": "42.2871,-2.5396", "key": "la_rioja" },
          { "name": "Las Palmas", "coordinates": "28.1235,-15.4363", "key": "las_palmas" },
          { "name": "León", "coordinates": "42.5987,-5.5671", "key": "leon" },
          { "name": "Lleida", "coordinates": "41.6176,0.6200", "key": "lleida" },
          { "name": "Lugo", "coordinates": "43.0125,-7.5550", "key": "lugo" },
          { "name": "Madrid", "coordinates": "40.4168,-3.7038", "key": "madrid" },
          { "name": "Málaga", "coordinates": "36.7213,-4.4214", "key": "malaga" },
          { "name": "Murcia", "coordinates": "37.9922,-1.1307", "key": "murcia" },
          { "name": "Navarra", "coordinates": "42.8125,-1.6458", "key": "navarra" },
          { "name": "Ourense", "coordinates": "42.3352,-7.8639", "key": "ourense" },
          { "name": "Palencia", "coordinates": "42.0095,-4.5270", "key": "palencia" },
          { "name": "Pontevedra", "coordinates": "42.4299,-8.6449", "key": "pontevedra" },
          { "name": "Salamanca", "coordinates": "40.9701,-5.6635", "key": "salamanca" },
          { "name": "Santa Cruz de Tenerife", "coordinates": "28.4636,-16.2518", "key": "santa_cruz_de_tenerife" },
          { "name": "Segovia", "coordinates": "40.9429,-4.1088", "key": "segovia" },
          { "name": "Sevilla", "coordinates": "37.3891,-5.9845", "key": "sevilla" },
          { "name": "Soria", "coordinates": "41.7636,-2.4651", "key": "soria" },
          { "name": "Tarragona", "coordinates": "41.1189,1.2445", "key": "tarragona" },
          { "name": "Teruel", "coordinates": "40.3452,-1.1069", "key": "teruel" },
          { "name": "Toledo", "coordinates": "39.8628,-4.0273", "key": "toledo" },
          { "name": "Valencia", "coordinates": "39.4699,-0.3763", "key": "valencia" },
          { "name": "Valladolid", "coordinates": "41.6520,-4.7286", "key": "valladolid" },
          { "name": "Vizcaya", "coordinates": "43.2630,-2.9350", "key": "vizcaya" },
          { "name": "Zamora", "coordinates": "41.5036,-5.7442", "key": "zamora" },
          { "name": "Zaragoza", "coordinates": "41.6488,-0.8891", "key": "zaragoza" }
      ]
      },
      {
        "key": "c",
        "name": "Europa",
        "locations": [
          { "name": "Albania", "capital": "Tirana", "coordinates": "41.3275,19.8189", "key": "albania" },
          { "name": "Alemania", "capital": "Berlín", "coordinates": "52.5200,13.4050", "key": "alemania" },
          { "name": "Andorra", "capital": "Andorra la Vieja", "coordinates": "42.5078,1.5211", "key": "andorra" },
          { "name": "Armenia", "capital": "Ereván", "coordinates": "40.1792,44.4991", "key": "armenia" },
          { "name": "Austria", "capital": "Viena", "coordinates": "48.2082,16.3738", "key": "austria" },
          { "name": "Bélgica", "capital": "Bruselas", "coordinates": "50.8503,4.3517", "key": "belgica" },
          { "name": "Bosnia y Herzegovina", "capital": "Sarajevo", "coordinates": "43.8563,18.4131", "key": "bosnia_y_herzegovina" },
          { "name": "Bulgaria", "capital": "Sofía", "coordinates": "42.6977,23.3219", "key": "bulgaria" },
          { "name": "Chipre", "capital": "Nicosia", "coordinates": "35.1856,33.3823", "key": "chipre" },
          { "name": "Croacia", "capital": "Zagreb", "coordinates": "45.8150,15.9819", "key": "croacia" },
          { "name": "Dinamarca", "capital": "Copenhague", "coordinates": "55.6761,12.5683", "key": "dinamarca" },
          { "name": "Eslovaquia", "capital": "Bratislava", "coordinates": "48.1486,17.1077", "key": "eslovaquia" },
          { "name": "Eslovenia", "capital": "Liubliana", "coordinates": "46.0569,14.5058", "key": "eslovenia" },
          { "name": "España", "capital": "Madrid", "coordinates": "40.4168,-3.7038", "key": "espana" },
          { "name": "Estonia", "capital": "Tallin", "coordinates": "59.4370,24.7536", "key": "estonia" },
          { "name": "Finlandia", "capital": "Helsinki", "coordinates": "60.1695,24.9355", "key": "finlandia" },
          { "name": "Francia", "capital": "París", "coordinates": "48.8566,2.3522", "key": "francia" },
          { "name": "Georgia", "capital": "Tiflis", "coordinates": "41.7151,44.8271", "key": "georgia" },
          { "name": "Grecia", "capital": "Atenas", "coordinates": "37.9838,23.7275", "key": "grecia" },
          { "name": "Hungría", "capital": "Budapest", "coordinates": "47.4979,19.0402", "key": "hungria" },
          { "name": "Irlanda", "capital": "Dublín", "coordinates": "53.3498,-6.2603", "key": "irlanda" },
          { "name": "Islandia", "capital": "Reikiavik", "coordinates": "64.1466,-21.9426", "key": "islandia" },
          { "name": "Italia", "capital": "Roma", "coordinates": "41.9028,12.4964", "key": "italia" },
          { "name": "Kazajistán", "capital": "Nursultán", "coordinates": "51.1694,71.4491", "key": "kazajistan" },
          { "name": "Letonia", "capital": "Riga", "coordinates": "56.9496,24.1052", "key": "letonia" },
          { "name": "Liechtenstein", "capital": "Vaduz", "coordinates": "47.1416,9.5215", "key": "liechtenstein" },
          { "name": "Lituania", "capital": "Vilna", "coordinates": "54.6872,25.2797", "key": "lituania" },
          { "name": "Luxemburgo", "capital": "Luxemburgo", "coordinates": "49.6117,6.1319", "key": "luxemburgo" },
          { "name": "Macedonia del Norte", "capital": "Skopie", "coordinates": "41.9981,21.4254", "key": "macedonia_del_norte" },
          { "name": "Malta", "capital": "La Valeta", "coordinates": "35.8997,14.5146", "key": "malta" },
          { "name": "Moldavia", "capital": "Chisináu", "coordinates": "47.0105,28.8638", "key": "moldavia" },
          { "name": "Mónaco", "capital": "Mónaco", "coordinates": "43.7384,7.4246", "key": "monaco" },
          { "name": "Montenegro", "capital": "Podgorica", "coordinates": "42.4304,19.2594", "key": "montenegro" },
          { "name": "Noruega", "capital": "Oslo", "coordinates": "59.9139,10.7522", "key": "noruega" },
          { "name": "Países Bajos", "capital": "Ámsterdam", "coordinates": "52.3676,4.9041", "key": "paises_bajos" },
          { "name": "Polonia", "capital": "Varsovia", "coordinates": "52.2297,21.0122", "key": "polonia" },
          { "name": "Portugal", "capital": "Lisboa", "coordinates": "38.7223,-9.1393", "key": "portugal" },
          { "name": "Reino Unido", "capital": "Londres", "coordinates": "51.5074,-0.1278", "key": "reino_unido" },
          { "name": "República Checa", "capital": "Praga", "coordinates": "50.0755,14.4378", "key": "republica_checa" },
          { "name": "Rumanía", "capital": "Bucarest", "coordinates": "44.4268,26.1025", "key": "rumania" },
          { "name": "Rusia", "capital": "Moscú", "coordinates": "55.7558,37.6173", "key": "rusia" },
          { "name": "San Marino", "capital": "San Marino", "coordinates": "43.9333,12.4500", "key": "san_marino" },
          { "name": "Serbia", "capital": "Belgrado", "coordinates": "44.7866,20.4489", "key": "serbia" },
          { "name": "Suecia", "capital": "Estocolmo", "coordinates": "59.3293,18.0686", "key": "suecia" },
          { "name": "Suiza", "capital": "Berna", "coordinates": "46.9481,7.4474", "key": "suiza" },
          { "name": "Turquía", "capital": "Ankara", "coordinates": "39.9334,32.8597", "key": "turquia" },
          { "name": "Ucrania", "capital": "Kiev", "coordinates": "50.4501,30.5234", "key": "ucrania" },
          { "name": "Vaticano", "capital": "Ciudad del Vaticano", "coordinates": "41.9029,12.4534", "key": "vaticano" }
      ]    
      },
      {
        "key": "b",
        "name": "America",
        "locations": [
          { "key": "antigua_y_barbuda", "name": "Antigua y Barbuda", "capital": "Saint John's", "coordinates": "17.1274,-61.8468" },
          { "key": "argentina", "name": "Argentina", "capital": "Buenos Aires", "coordinates": "-34.6037,-58.3816" },
          { "key": "bahamas", "name": "Bahamas", "capital": "Nasáu", "coordinates": "25.0343,-77.3963" },
          { "key": "barbados", "name": "Barbados", "capital": "Bridgetown", "coordinates": "13.1132,-59.5988" },
          { "key": "belice", "name": "Belice", "capital": "Belmopán", "coordinates": "17.2510,-88.7590" },
          { "key": "bolivia", "name": "Bolivia", "capital": "La Paz", "coordinates": "-16.5000,-68.1500" },
          { "key": "brasil", "name": "Brasil", "capital": "Brasilia", "coordinates": "-15.8267,-47.9218" },
          { "key": "canada", "name": "Canadá", "capital": "Ottawa", "coordinates": "45.4215,-75.6972" },
          { "key": "chile", "name": "Chile", "capital": "Santiago", "coordinates": "-33.4489,-70.6693" },
          { "key": "colombia", "name": "Colombia", "capital": "Bogotá", "coordinates": "4.7110,-74.0721" },
          { "key": "costa_rica", "name": "Costa Rica", "capital": "San José", "coordinates": "9.9281,-84.0907" },
          { "key": "cuba", "name": "Cuba", "capital": "La Habana", "coordinates": "23.1136,-82.3666" },
          { "key": "dominica", "name": "Dominica", "capital": "Roseau", "coordinates": "15.3092,-61.3794" },
          { "key": "ecuador", "name": "Ecuador", "capital": "Quito", "coordinates": "-0.1807,-78.4678" },
          { "key": "el_salvador", "name": "El Salvador", "capital": "San Salvador", "coordinates": "13.6929,-89.2182" },
          { "key": "estados_unidos", "name": "Estados Unidos", "capital": "Washington D.C.", "coordinates": "38.9072,-77.0369" },
          { "key": "granada", "name": "Granada", "capital": "Saint George's", "coordinates": "12.0561,-61.7488" },
          { "key": "guatemala", "name": "Guatemala", "capital": "Ciudad de Guatemala", "coordinates": "14.6349,-90.5069" },
          { "key": "guyana", "name": "Guyana", "capital": "Georgetown", "coordinates": "6.8013,-58.1551" },
          { "key": "haiti", "name": "Haití", "capital": "Puerto Príncipe", "coordinates": "18.5944,-72.3074" },
          { "key": "honduras", "name": "Honduras", "capital": "Tegucigalpa", "coordinates": "14.0723,-87.1921" },
          { "key": "jamaica", "name": "Jamaica", "capital": "Kingston", "coordinates": "18.0179,-76.8099" },
          { "key": "mexico", "name": "México", "capital": "Ciudad de México", "coordinates": "19.4326,-99.1332" },
          { "key": "nicaragua", "name": "Nicaragua", "capital": "Managua", "coordinates": "12.1150,-86.2362" },
          { "key": "panama", "name": "Panamá", "capital": "Ciudad de Panamá", "coordinates": "8.9824,-79.5199" },
          { "key": "paraguay", "name": "Paraguay", "capital": "Asunción", "coordinates": "-25.2637,-57.5759" },
          { "key": "peru", "name": "Perú", "capital": "Lima", "coordinates": "-12.0464,-77.0428" },
          { "key": "republica_dominicana", "name": "República Dominicana", "capital": "Santo Domingo", "coordinates": "18.4861,-69.9312" },
          { "key": "san_cristobal_y_nieves", "name": "San Cristóbal y Nieves", "capital": "Basseterre", "coordinates": "17.3026,-62.7177" },
          { "key": "san_vicente_y_las_granadinas", "name": "San Vicente y las Granadinas", "capital": "Kingstown", "coordinates": "13.1600,-61.2248" },
          { "key": "santa_lucia", "name": "Santa Lucía", "capital": "Castries", "coordinates": "14.0101,-60.9875" },
          { "key": "surinam", "name": "Surinam", "capital": "Paramaribo", "coordinates": "5.8520,-55.2038" },
          { "key": "trinidad_y_tobago", "name": "Trinidad y Tobago", "capital": "Puerto España", "coordinates": "10.6918,-61.2225" },
          { "key": "uruguay", "name": "Uruguay", "capital": "Montevideo", "coordinates": "-34.9011,-56.1645" },
          { "key": "venezuela", "name": "Venezuela", "capital": "Caracas", "coordinates": "10.4806,-66.9036" }
      ]    
      },
      {
        "key": "d",
        "name": "Otro",
        "locations": [
        ]
      }
    ]
  }